bardata/__init__.py
bardata/config.py
bardata/dates.py
bardata/errors.py
bardata/freqs.py
bardata/massive/__init__.py
bardata/massive/engine.py
bardata/massive/utils.py
bardata/model.py
bardata/prices.py
bardata/random.py
bardata/samples/__init__.py
bardata/samples/daily-prices.csv
bardata/samples/hourly-prices.csv
bardata/samples/minute-prices.csv
bardata/scanner.py
bardata/tests/test_bardata.py
bardata/tiingo/__init__.py
bardata/tiingo/engine.py
bardata/tiingo/utils.py
bardata/utils.py
bardata/yahoo/__init__.py
bardata/yahoo/engine.py
bardata/yahoo/utils.py
bardata-0.0.6.dist-info/WHEEL
bardata-0.0.6.dist-info/entry_points.txt
bardata-0.0.6.dist-info/METADATA
bardata-0.0.6.dist-info/RECORD
