Metadata-Version: 2.4
Name: bardata
Version: 0.0.6
Summary: Unified api to fetch stock prices from varied sources
Keywords: finance,data
Author: Furechan
Author-email: Furechan <furechan@xsmail.com>
License-Expression: MIT
Classifier: Programming Language :: Python :: 3
Requires-Dist: numpy
Requires-Dist: pandas
Requires-Dist: yfinance ; extra == 'all'
Requires-Dist: tiingo ; extra == 'all'
Requires-Dist: massive ; extra == 'all'
Requires-Dist: massive ; extra == 'massive'
Requires-Dist: tiingo ; extra == 'tiingo'
Requires-Dist: yfinance ; extra == 'yahoo'
Requires-Python: >=3.10
Provides-Extra: all
Provides-Extra: massive
Provides-Extra: tiingo
Provides-Extra: yahoo
